asdf_compression/__init__.py
asdf_compression/_utils.py
asdf_compression/_version.py
asdf_compression/extensions.py
asdf_compression/_tests/__init__.py
asdf_compression/_tests/test_labels.py
asdf_compression/blsc/__init__.py
asdf_compression/blsc/compressor.py
asdf_compression/blsc/extensions.py
asdf_compression/lz4f/__init__.py
asdf_compression/lz4f/compressor.py
asdf_compression/lz4f/extensions.py
asdf_compression/zstd/__init__.py
asdf_compression/zstd/compressor.py
asdf_compression/zstd/extensions.py
asdf_compression-0.1.0.dist-info/licenses/LICENSE
asdf_compression-0.1.0.dist-info/METADATA
asdf_compression-0.1.0.dist-info/WHEEL
asdf_compression-0.1.0.dist-info/entry_points.txt
asdf_compression-0.1.0.dist-info/top_level.txt
asdf_compression-0.1.0.dist-info/RECORD
