Metadata-Version: 2.4
Name: asdf_compression
Version: 0.1.0
Summary: Asdf extension to support various compression algorithms
Author: The ASDF Developers
Project-URL: documentation, https://asdf-compression.readthedocs.io/en/latest
Project-URL: repository, https://github.com/asdf-format/asdf-compression
Project-URL: tracker, https://github.com/asdf-format/asdf-compression/issues
Classifier: Development Status :: 5 - Production/Stable
Classifier: Programming Language :: Python
Classifier: Programming Language :: Python :: 3
Requires-Python: >=3.10
License-File: LICENSE
Requires-Dist: asdf>=2.15
Provides-Extra: tests
Requires-Dist: pytest>=6; extra == "tests"
Provides-Extra: blsc
Requires-Dist: blosc>=1.9.2; extra == "blsc"
Provides-Extra: lz4f
Requires-Dist: lz4>=0.10; extra == "lz4f"
Provides-Extra: zstd
Requires-Dist: zstandard>=0.21.0; extra == "zstd"
Provides-Extra: all
Requires-Dist: asdf_compression[blsc,lz4f,zstd]; extra == "all"
Dynamic: license-file
